basic_utils/__init__.py
basic_utils/core.py
basic_utils/date_helpers.py
basic_utils/dict_helpers.py
basic_utils/primitives.py
basic_utils/seq_helpers.py
basic_utils-1.6.0.dist-info/DESCRIPTION.rst
basic_utils-1.6.0.dist-info/METADATA
basic_utils-1.6.0.dist-info/RECORD
basic_utils-1.6.0.dist-info/WHEEL
basic_utils-1.6.0.dist-info/metadata.json
basic_utils-1.6.0.dist-info/top_level.txt
